report_generator.py
seo_analyzer.py
seo_api_client.py
seo_checker.py
website_crawler.py
seo_website_analyzer-1.0.1.dist-info/METADATA
seo_website_analyzer-1.0.1.dist-info/WHEEL
seo_website_analyzer-1.0.1.dist-info/entry_points.txt
seo_website_analyzer-1.0.1.dist-info/top_level.txt
seo_website_analyzer-1.0.1.dist-info/RECORD
