Metadata-Version: 2.4
Name: seo-website-analyzer
Version: 1.0.1
Summary: Comprehensive website SEO optimization checker that automatically crawls all pages of a specified domain and performs thorough SEO analysis
Author: SEO Website Analyzer Team
License-Expression: MIT
Project-URL: Homepage, https://github.com/yourusername/seo-website-analyzer
Project-URL: Documentation, https://github.com/yourusername/seo-website-analyzer#readme
Project-URL: Repository, https://github.com/yourusername/seo-website-analyzer
Project-URL: Issues, https://github.com/yourusername/seo-website-analyzer/issues
Keywords: seo,analyzer,website,crawler,optimization,audit
Classifier: Development Status :: 4 - Beta
Classifier: Intended Audience :: Developers
Classifier: Programming Language :: Python :: 3
Classifier: Programming Language :: Python :: 3.7
Classifier: Programming Language :: Python :: 3.8
Classifier: Programming Language :: Python :: 3.9
Classifier: Programming Language :: Python :: 3.10
Classifier: Programming Language :: Python :: 3.11
Classifier: Topic :: Software Development :: Libraries :: Python Modules
Classifier: Topic :: Internet :: WWW/HTTP :: Indexing/Search
Classifier: Topic :: Text Processing :: Markup :: HTML
Requires-Python: >=3.7
Requires-Dist: requests>=2.25.1
Requires-Dist: beautifulsoup4>=4.9.3
Requires-Dist: lxml>=4.6.3
Requires-Dist: openpyxl>=3.0.7
Requires-Dist: pandas>=1.3.0
Provides-Extra: dev
Requires-Dist: pytest>=6.0; extra == "dev"
Requires-Dist: black>=21.0; extra == "dev"
Requires-Dist: flake8>=3.8; extra == "dev"
Provides-Extra: visualization
Requires-Dist: matplotlib>=3.4.2; extra == "visualization"
Requires-Dist: seaborn>=0.11.1; extra == "visualization"
Requires-Dist: plotly>=5.0.0; extra == "visualization"
